{
    "event": {
        "kind": "t_weijian",
        "id": 10,
        "session": 100,
        "content": [
            {
                "s_netid": "1",
                "s_villagename": "村名1",
                "s_netname": "网格99",
                "s_eventtype": "事件类型",
                "s_eventid": "事件ID",
                "t_tijiao": "2013-01-02",
                "s_discoverername": "发现人",
                "s_discovererlevel": "发现人级别",
                "s_solvestatus": "解决状态",
                "s_result": "解决结果",
                "t_solvetime": "2013-01-02",
                "s_unsolvedreason": "未解决原因",
                
                "s_photo":"http://aa/aa/img.jpg现场照片",
                "t_photouploaddate":"2013-01-02",
                "s_photoposition":"照片地理信息",
                "s_photouploadperson":"照片上传人",
                "s_photouploadlevel":"照片上传人级别",
                "s_video":"现场视频",
                "t_videouploaddate":"2013-01-02",
                "s_videouploadperson":"视频上传人",
                "s_videouploadlevel":"视频上传人级别",
                
                "s_leaderinstruction": "领导批示",
                "s_voiceinstruction": "语音批示",
                "t_instructiondate": "2013-01-02",
                "s_leaderid": "批示人id",
                "s_leadername": "批示人姓名",
                "s_netleadername": "格长姓名",
                "s_netleadertel": "格长电话",
                "s_updatename": "最近更新人",
                "s_updatelevel": "更新人级别",
                "t_updatetime": "2013-01-02",
                "s_remark": "备注",
                
                "s_yinhuanaddress": "违法建设具体位置",
                "s_weijianxiangduiren": "违法建设相对人",
                "s_yinhuanxiangqing": "违章描述",
                "s_landstatus": "土地性质",
                "d_landarea": 100.2,
                "s_construction": "建筑结构",
                "d_jianzhumianji": 100.3,
                "t_buildtime": "2013-01-02",
                "s_solvemethod": "当日新发现和拆除情况",
                "s_yinhuanren": "涉及人姓名",
                "s_yinhuanlianluo": "涉及人联系方式",
                "t_jianshedate": "2013-01-02",
                "d_latitude": 38.112,
                "d_longitude": 116.002
 
            },
            {
                "s_netid": "2",
                "s_villagename": "村名2",
                "s_netname": "网格92",
                "s_eventtype": "事件类型",
                "s_eventid": "事件ID2",
                "t_tijiao": "2013-01-12",
                "s_discoverername": "发现人",
                "s_discovererlevel": "发现人级别",
                "s_solvestatus": "解决状态",
                "s_result": "解决结果",
                "t_solvetime": "2013-01-02",
                "s_unsolvedreason": "未解决原因",
                
                "s_photo":"http://aa/aa/img.jpg现场照片",
                "t_photouploaddate":"2013-01-02",
                "s_photoposition":"照片地理信息",
                "s_photouploadperson":"照片上传人",
                "s_photouploadlevel":"照片上传人级别",
                "s_video":"现场视频",
                "t_videouploaddate":"2013-01-02",
                "s_videouploadperson":"视频上传人",
                "s_videouploadlevel":"视频上传人级别",
                
                "s_leaderinstruction": "领导批示",
                "s_voiceinstruction": "语音批示",
                "t_instructiondate": "2013-01-02",
                "s_leaderid": "批示人id",
                "s_leadername": "批示人姓名",
                "s_netleadername": "格长姓名",
                "s_netleadertel": "格长电话",
                "s_updatename": "最近更新人",
                "s_updatelevel": "更新人级别",
                "t_updatetime": "2013-01-02",
                "s_remark": "备注",
                
                "s_yinhuanaddress": "违法建设具体位置",
                "s_weijianxiangduiren": "违法建设相对人",
                "s_yinhuanxiangqing": "违章描述",
                "s_landstatus": "土地性质",
                "d_landarea": 100.2,
                "s_construction": "建筑结构",
                "d_jianzhumianji": 100.3,
                "t_buildtime": "2013-01-02",
                "s_solvemethod": "当日新发现和拆除情况",
                "s_yinhuanren": "涉及人姓名",
                "s_yinhuanlianluo": "涉及人联系方式",
                "t_jianshedate": "2013-01-02",
                "d_latitude": 38.112,
                "d_longitude": 116.002
 
            },
                        {
                "s_netid": "3",
                "s_villagename": "村名3",
                "s_netname": "网格93",
                "s_eventtype": "事件类型",
                "s_eventid": "事件ID3",
                "t_tijiao": "2013-01-02",
                "s_discoverername": "发现人",
                "s_discovererlevel": "发现人级别",
                "s_solvestatus": "解决状态",
                "s_result": "解决结果",
                "t_solvetime": "2013-01-02",
                "s_unsolvedreason": "未解决原因",
                
                "s_photo":"http://aa/aa/img.jpg现场照片",
                "t_photouploaddate":"2013-01-02",
                "s_photoposition":"照片地理信息",
                "s_photouploadperson":"照片上传人",
                "s_photouploadlevel":"照片上传人级别",
                "s_video":"现场视频",
                "t_videouploaddate":"2013-01-02",
                "s_videouploadperson":"视频上传人",
                "s_videouploadlevel":"视频上传人级别",
                
                "s_leaderinstruction": "领导批示",
                "s_voiceinstruction": "语音批示",
                "t_instructiondate": "2013-01-02",
                "s_leaderid": "批示人id",
                "s_leadername": "批示人姓名",
                "s_netleadername": "格长姓名",
                "s_netleadertel": "格长电话",
                "s_updatename": "最近更新人",
                "s_updatelevel": "更新人级别",
                "t_updatetime": "2013-01-02",
                "s_remark": "备注",
                
                "s_yinhuanaddress": "违法建设具体位置",
                "s_weijianxiangduiren": "违法建设相对人",
                "s_yinhuanxiangqing": "违章描述",
                "s_landstatus": "土地性质",
                "d_landarea": 100.2,
                "s_construction": "建筑结构",
                "d_jianzhumianji": 100.3,
                "t_buildtime": "2013-01-02",
                "s_solvemethod": "当日新发现和拆除情况",
                "s_yinhuanren": "涉及人姓名",
                "s_yinhuanlianluo": "涉及人联系方式",
                "t_jianshedate": "2013-01-02",
                "d_latitude": 38.112,
                "d_longitude": 116.002
 
            },
            {
                "s_netid": "4",
                "s_villagename": "村名4",
                "s_netname": "网格94",
                "s_eventtype": "事件类型",
                "s_eventid": "事件ID4",
                "t_tijiao": "2013-01-02",
                "s_discoverername": "发现人",
                "s_discovererlevel": "发现人级别",
                "s_solvestatus": "解决状态",
                "s_result": "解决结果",
                "t_solvetime": "2013-01-02",
                "s_unsolvedreason": "未解决原因",
                
                "s_photo":"http://aa/aa/img.jpg现场照片",
                "t_photouploaddate":"2013-01-02",
                "s_photoposition":"照片地理信息",
                "s_photouploadperson":"照片上传人",
                "s_photouploadlevel":"照片上传人级别",
                "s_video":"现场视频",
                "t_videouploaddate":"2013-01-02",
                "s_videouploadperson":"视频上传人",
                "s_videouploadlevel":"视频上传人级别",
                
                "s_leaderinstruction": "领导批示",
                "s_voiceinstruction": "语音批示",
                "t_instructiondate": "2013-01-02",
                "s_leaderid": "批示人id",
                "s_leadername": "批示人姓名",
                "s_netleadername": "格长姓名",
                "s_netleadertel": "格长电话",
                "s_updatename": "最近更新人",
                "s_updatelevel": "更新人级别",
                "t_updatetime": "2013-01-02",
                "s_remark": "备注",
                
                "s_yinhuanaddress": "违法建设具体位置",
                "s_weijianxiangduiren": "违法建设相对人",
                "s_yinhuanxiangqing": "违章描述",
                "s_landstatus": "土地性质",
                "d_landarea": 100.2,
                "s_construction": "建筑结构",
                "d_jianzhumianji": 100.3,
                "t_buildtime": "2013-01-02",
                "s_solvemethod": "当日新发现和拆除情况",
                "s_yinhuanren": "涉及人姓名",
                "s_yinhuanlianluo": "涉及人联系方式",
                "t_jianshedate": "2013-01-02",
                "d_latitude": 38.112,
                "d_longitude": 116.002
 
            }
        ]
    }
}